authanor/_version.py
authanor/database/__init__.py
authanor/database/handler.py
authanor/database/models.py
authanor/database/utils.py
authanor/testing/__init__.py
authanor/testing/helpers.py
authanor-1.1.1.dist-info/METADATA
authanor-1.1.1.dist-info/WHEEL
authanor-1.1.1.dist-info/entry_points.txt
authanor-1.1.1.dist-info/licenses/COPYING
authanor-1.1.1.dist-info/licenses/LICENSE
authanor-1.1.1.dist-info/RECORD
